hub_sdk/__init__.py
hub_sdk/_modidx.py
hub_sdk/core.py
fewsats_hub-0.0.1.dist-info/LICENSE
fewsats_hub-0.0.1.dist-info/METADATA
fewsats_hub-0.0.1.dist-info/WHEEL
fewsats_hub-0.0.1.dist-info/entry_points.txt
fewsats_hub-0.0.1.dist-info/top_level.txt
fewsats_hub-0.0.1.dist-info/RECORD
