Metadata-Version: 2.1
Name: fewsats-hub
Version: 0.0.1
Summary: Python SDK for Fewsats Hub
Home-page: https://github.com/fewsats/hub-sdk
Author: Pol Alvarez & Jordi Montes
Author-email: pol@fewsats.com
License: Apache Software License 2.0
Keywords: nbdev jupyter notebook python
Classifier: Development Status :: 4 - Beta
Classifier: Intended Audience :: Developers
Classifier: Natural Language :: English
Classifier: Programming Language :: Python :: 3.9
Classifier: Programming Language :: Python :: 3.10
Classifier: License :: OSI Approved :: Apache Software License
Requires-Python: >=3.9
License-File: LICENSE
Requires-Dist: fastcore >=1.7.1
Requires-Dist: requests
Provides-Extra: dev
